scikit_plots.libs/libgcc_s-0cd532bd.so.1
scikit_plots.libs/libstdc++-5d72f927.so.6.0.33
scikitplot/__init__.py
scikitplot/__init__.pyi
scikitplot/__main__.py
scikitplot/_globals.py
scikitplot/_globals.pyi
scikitplot/_logo.py
scikitplot/_magic.py
scikitplot/_min_dependencies.py
scikitplot/_preprocess.py
scikitplot/_preprocess.pyi
scikitplot/_reset.py
scikitplot/annoy.pxd
scikitplot/cexperimental.pxd
scikitplot/cexternals.pxd
scikitplot/conftest.py
scikitplot/dummy.py
scikitplot/environment_variables.py
scikitplot/exceptions.py
scikitplot/exceptions.pyi
scikitplot/logging.py
scikitplot/meson.build
scikitplot/ml-package-versions.yml
scikitplot/ml_package_versions.py
scikitplot/nc.pxd
scikitplot/py.typed
scikitplot/version.py
scikitplot/version.pyi
scikitplot/_api/__init__.py
scikitplot/_api/__init__.pyi
scikitplot/_api/deprecation.py
scikitplot/_api/deprecation.pyi
scikitplot/_api/meson.build
scikitplot/_build_utils/__init__.py
scikitplot/_build_utils/copyfiles.py
scikitplot/_build_utils/cythoner.py
scikitplot/_build_utils/fix_submodule_import.py
scikitplot/_build_utils/gcc_build_bitness.py
scikitplot/_build_utils/gitversion.py
scikitplot/_build_utils/link-version-pyinit.map
scikitplot/_build_utils/system_info.py
scikitplot/_build_utils/tempita.py
scikitplot/_build_utils/version.py
scikitplot/_cli/_cmdoptions_click.py
scikitplot/_cli/_cmdoptions_optparse.py
scikitplot/_cli/_misc.py
scikitplot/_cli/cli.py
scikitplot/_cli/_commands/__init__.py
scikitplot/_cli/_commands/greet.py
scikitplot/_cli/_commands/show_config.py
scikitplot/_cli/_commands/show_versions.py
scikitplot/_cli/_commands/sysinfo.py
scikitplot/_compat/__init__.py
scikitplot/_compat/_sklearn.py
scikitplot/_compat/numpycompat.py
scikitplot/_compat/optional_deps.py
scikitplot/_compat/python.py
scikitplot/_datasets/__init__.py
scikitplot/_datasets/data_loader.py
scikitplot/_decorates/__init__.py
scikitplot/_decorates/_decorate.py
scikit_plots-0.4.0.post9.dist-info/LICENSE.txt
scikit_plots-0.4.0.post9.dist-info/METADATA
scikit_plots-0.4.0.post9.dist-info/WHEEL
scikit_plots-0.4.0.post9.dist-info/entry_points.txt
scikit_plots-0.4.0.post9.dist-info/RECORD
