Metadata-Version: 2.1
Name: scikit-plots
Version: 0.4.0.post9
Summary: An intuitive library that seamlessly adds plotting capabilities and functionality to any model objects or outputs, compatible with tools like scikit-learn, XGBoost, TensorFlow, and more.
Keywords: ai,data science,machine learning,visualization,matplotlib,scikit-learn,xgboost,catboost,tensorflow,keras,pytorch,transformers
Author-Email: scikit-plots developers <scikit-plots-dev@googlegroups.com>
Maintainer-Email: scikit-plots developers <scikit-plots-maintainers@googlegroups.com>
License: BSD 3-Clause License
Classifier: Development Status :: 3 - Alpha
Classifier: Framework :: Matplotlib
Classifier: Intended Audience :: Developers
Classifier: Intended Audience :: End Users/Desktop
Classifier: Intended Audience :: Science/Research
Classifier: Natural Language :: English
Classifier: Operating System :: Microsoft :: Windows
Classifier: Operating System :: POSIX
Classifier: Operating System :: POSIX :: Linux
Classifier: Operating System :: Unix
Classifier: Operating System :: MacOS
Classifier: Programming Language :: C
Classifier: Programming Language :: C++
Classifier: Programming Language :: Fortran
Classifier: Programming Language :: Cython
Classifier: Programming Language :: Python
Classifier: Programming Language :: Python :: 3 :: Only
Classifier: Programming Language :: Python :: 3
Classifier: Programming Language :: Python :: 3.8
Classifier: Programming Language :: Python :: 3.9
Classifier: Programming Language :: Python :: 3.10
Classifier: Programming Language :: Python :: 3.11
Classifier: Programming Language :: Python :: 3.12
Classifier: Programming Language :: Python :: 3.13
Classifier: Programming Language :: Python :: 3.14
Classifier: Programming Language :: Python :: Implementation :: CPython
Classifier: Topic :: Scientific/Engineering :: Artificial Intelligence
Classifier: Topic :: Scientific/Engineering :: Visualization
Classifier: Topic :: Software Development :: Libraries
Classifier: Topic :: Software Development :: Libraries :: Python Modules
Classifier: Topic :: Multimedia :: Graphics
Classifier: Typing :: Typed
Project-URL: homepage, https://scikit-plots.github.io
Project-URL: repository, https://github.com/scikit-plots/scikit-plots
Project-URL: download, https://github.com/scikit-plots/scikit-plots/tags
Project-URL: changelog, https://scikit-plots.github.io/dev/whats_new/index.html
Project-URL: documentation, https://scikit-plots.github.io
Project-URL: issues, https://github.com/scikit-plots/scikit-plots/issues
Requires-Python: >=3.8
Requires-Dist: numpy!=1.24.0,>=1.20; python_version < "3.9"
Requires-Dist: numpy>=2.0.0; python_version >= "3.9"
Requires-Dist: scipy>=1.7.0
Requires-Dist: matplotlib!=3.6.1,>=3.4
Requires-Dist: pandas>=1.2.0
Requires-Dist: scikit-learn>=1.3.0rc1
Requires-Dist: joblib>=1.2.0
Requires-Dist: threadpoolctl>=3.1.0
Provides-Extra: legacy
Requires-Dist: numpy!=1.24.0,>=1.20; python_version < "3.9" and extra == "legacy"
Requires-Dist: importlib-metadata; python_version < "3.10" and extra == "legacy"
Requires-Dist: tomli; python_version < "3.11" and extra == "legacy"
Requires-Dist: tomli-w; python_version < "3.11" and extra == "legacy"
Requires-Dist: toml; python_version < "3.11" and extra == "legacy"
Provides-Extra: core
Requires-Dist: seaborn>=0.11; extra == "core"
Requires-Dist: aggdraw>=1.3.11; sys_platform != "emscripten" and extra == "core"
Requires-Dist: pillow>=6.2.0; extra == "core"
Requires-Dist: voyager>=1.2.5; extra == "core"
Provides-Extra: build
Requires-Dist: scikit-plots[legacy]; extra == "build"
Requires-Dist: scikit-plots[core]; extra == "build"
Requires-Dist: build; extra == "build"
Requires-Dist: twine; extra == "build"
Requires-Dist: meson>=1.5.0; extra == "build"
Requires-Dist: ninja>=1.11.0; extra == "build"
Requires-Dist: meson-python>=0.16.0; extra == "build"
Requires-Dist: cython>=3.0.8; extra == "build"
Requires-Dist: pybind11>=2.13.2; extra == "build"
Requires-Dist: pythran>=0.14.0; extra == "build"
Requires-Dist: numpy!=1.24.0,>=1.20; python_version < "3.9" and extra == "build"
Requires-Dist: numpy>=2.0.0; python_version >= "3.9" and extra == "build"
Provides-Extra: dev
Requires-Dist: scikit-plots[core]; extra == "dev"
Requires-Dist: packaging; extra == "dev"
Requires-Dist: pandas-stubs; extra == "dev"
Requires-Dist: pycodestyle; extra == "dev"
Requires-Dist: pydantic; extra == "dev"
Requires-Dist: pydevtool; extra == "dev"
Requires-Dist: pyyaml; extra == "dev"
Requires-Dist: types-psutil; extra == "dev"
Requires-Dist: typing_extensions; extra == "dev"
Requires-Dist: requests; extra == "dev"
Requires-Dist: click; extra == "dev"
Requires-Dist: rich-click; extra == "dev"
Requires-Dist: doit; extra == "dev"
Requires-Dist: pre-commit; extra == "dev"
Requires-Dist: cython-lint; extra == "dev"
Requires-Dist: flake8; extra == "dev"
Requires-Dist: black; extra == "dev"
Requires-Dist: ruff; extra == "dev"
Requires-Dist: mypy; extra == "dev"
Provides-Extra: test-nogil
Requires-Dist: scikit-plots[core]; extra == "test-nogil"
Requires-Dist: hypothesis; extra == "test-nogil"
Requires-Dist: pytest>=7.1.2; extra == "test-nogil"
Requires-Dist: pytest-cov; extra == "test-nogil"
Requires-Dist: pytest-fail-slow; extra == "test-nogil"
Requires-Dist: pytest-mpl; extra == "test-nogil"
Requires-Dist: pytest-run-parallel; extra == "test-nogil"
Requires-Dist: pytest-timeout; extra == "test-nogil"
Requires-Dist: pytest-xdist; extra == "test-nogil"
Requires-Dist: asv; extra == "test-nogil"
Requires-Dist: mpmath; extra == "test-nogil"
Requires-Dist: tenacity; extra == "test-nogil"
Requires-Dist: pyinstrument; extra == "test-nogil"
Provides-Extra: test
Requires-Dist: scikit-plots[test_nogil]; extra == "test"
Requires-Dist: h5py<=3.11.0; python_version < "3.10" and extra == "test"
Requires-Dist: h5py; python_version >= "3.10" and extra == "test"
Provides-Extra: emscripten-test
Requires-Dist: hypothesis>=6.130.0; extra == "emscripten-test"
Requires-Dist: pytest>=7.1.2; extra == "emscripten-test"
Requires-Dist: pytest-xdist; extra == "emscripten-test"
Requires-Dist: tzdata; extra == "emscripten-test"
Provides-Extra: doc
Requires-Dist: scikit-plots[core]; extra == "doc"
Requires-Dist: sphinx<100.0.0,>=5.0.0; extra == "doc"
Requires-Dist: sphinx-copybutton; extra == "doc"
Requires-Dist: sphinx-design; extra == "doc"
Requires-Dist: sphinx-gallery; extra == "doc"
Requires-Dist: sphinx-prompt; extra == "doc"
Requires-Dist: sphinx-remove-toctrees; extra == "doc"
Requires-Dist: sphinx-rtd-theme; extra == "doc"
Requires-Dist: sphinx-tabs; extra == "doc"
Requires-Dist: sphinx-tags; extra == "doc"
Requires-Dist: sphinxext-opengraph; extra == "doc"
Requires-Dist: sphinxcontrib-inlinesyntaxhighlight; extra == "doc"
Requires-Dist: sphinxcontrib-sass; extra == "doc"
Requires-Dist: sphinxcontrib-svg2pdfconverter; extra == "doc"
Requires-Dist: pydata-sphinx-theme; extra == "doc"
Requires-Dist: colorspacious; extra == "doc"
Requires-Dist: jinja2; extra == "doc"
Requires-Dist: jupyter-sphinx; extra == "doc"
Requires-Dist: jupyterlite-pyodide-kernel; extra == "doc"
Requires-Dist: jupyterlite-sphinx; extra == "doc"
Requires-Dist: jupytext; extra == "doc"
Requires-Dist: intersphinx_registry; extra == "doc"
Requires-Dist: numpydoc; extra == "doc"
Requires-Dist: myst-nb; extra == "doc"
Requires-Dist: myst-parser; extra == "doc"
Requires-Dist: packaging; extra == "doc"
Requires-Dist: pooch; extra == "doc"
Requires-Dist: towncrier; extra == "doc"
Requires-Dist: catboost; extra == "doc"
Requires-Dist: xgboost; extra == "doc"
Provides-Extra: maintenance
Requires-Dist: conda-lock>=3.0.0; extra == "maintenance"
Provides-Extra: cpu
Requires-Dist: tensorflow-cpu; extra == "cpu"
Requires-Dist: transformers; extra == "cpu"
Requires-Dist: tf-keras; extra == "cpu"
Provides-Extra: gpu
Requires-Dist: cupy-cuda12x; extra == "gpu"
Requires-Dist: sentence-transformers; extra == "gpu"
Provides-Extra: tpu
Requires-Dist: tensorflow; extra == "tpu"
Requires-Dist: transformers; extra == "tpu"
Requires-Dist: tf-keras; extra == "tpu"
Provides-Extra: extend
Requires-Dist: statsmodels>=0.12; extra == "extend"
Requires-Dist: catboost; extra == "extend"
Requires-Dist: xgboost; extra == "extend"
Requires-Dist: scikit-image; extra == "extend"
Requires-Dist: plotly; extra == "extend"
Requires-Dist: polars; extra == "extend"
Requires-Dist: pyarrow; extra == "extend"
Provides-Extra: ci32-requirements
Requires-Dist: scipy-openblas32==0.3.29.265.1; extra == "ci32-requirements"
Requires-Dist: spin; extra == "ci32-requirements"
Provides-Extra: ci-requirements
Requires-Dist: scikit-plots[ci32_requirements]; extra == "ci-requirements"
Requires-Dist: scipy-openblas64==0.3.29.265.1; extra == "ci-requirements"
